concierge_cli/__init__.py
concierge_cli/__main__.py
concierge_cli/adapter.py
concierge_cli/cli.py
concierge_cli/constants.py
concierge_cli/manager.py
concierge_cli-1.7.2.dist-info/LICENSE
concierge_cli-1.7.2.dist-info/METADATA
concierge_cli-1.7.2.dist-info/WHEEL
concierge_cli-1.7.2.dist-info/entry_points.txt
concierge_cli-1.7.2.dist-info/top_level.txt
concierge_cli-1.7.2.dist-info/RECORD
