Metadata-Version: 2.1
Name: concierge-cli
Version: 1.7.2
Summary: Concierge repository projects management CLI.
Home-page: https://github.com/vshn/concierge-cli
Author: VSHN AG
Author-email: tech@vshn.ch
License: BSD-3-Clause
Keywords: cli,gitlab,maintenance
Classifier: Development Status :: 4 - Beta
Classifier: Intended Audience :: Developers
Classifier: Intended Audience :: System Administrators
Classifier: License :: OSI Approved :: BSD License
Classifier: Programming Language :: Python
Classifier: Programming Language :: Python :: 3 :: Only
Classifier: Programming Language :: Python :: 3.6
Classifier: Programming Language :: Python :: 3.7
Classifier: Programming Language :: Python :: 3.8
Classifier: Programming Language :: Python :: 3.9
Classifier: Programming Language :: Python :: 3.10
Requires-Python: >=3.6
License-File: LICENSE
Requires-Dist: click
Requires-Dist: python-gitlab
